django_pygments/__init__.py
django_pygments/models.py
django_pygments/urls.py
django_pygments/utils.py
django_pygments/views.py
django_pygments/static/django_pygments/css/demo.css
django_pygments/static/django_pygments/css/pygments_default.css
django_pygments/templates/django_pygments/demo.html
django_pygments/templatetags/__init__.py
django_pygments/templatetags/pygmentify.py
django_pygments-0.8.dist-info/AUTHORS
django_pygments-0.8.dist-info/LICENSE
django_pygments-0.8.dist-info/METADATA
django_pygments-0.8.dist-info/WHEEL
django_pygments-0.8.dist-info/top_level.txt
django_pygments-0.8.dist-info/RECORD
