Metadata-Version: 2.1
Name: django-pygments
Version: 0.8
Summary: Django app that provides a template tag and 2 filters for                 doing syntax highlighting with Pygments
Home-page: http://github.com/stefantalpalaru/django-pygments
Author: Ștefan Talpalaru
Author-email: stefantalpalaru@yahoo.com
Classifier: Environment :: Web Environment
Classifier: Intended Audience :: Developers
Classifier: Operating System :: OS Independent
Classifier: Programming Language :: Python
Classifier: Programming Language :: Python :: 2
Classifier: Programming Language :: Python :: 3
Classifier: Framework :: Django
License-File: LICENSE
License-File: AUTHORS
Requires-Dist: pygments
